check_link/__init__.py
check_link/base.py
check_link/blocking.py
check_link/checker.py
check_link-0.0.11.dist-info/METADATA
check_link-0.0.11.dist-info/WHEEL
check_link-0.0.11.dist-info/entry_points.txt
check_link-0.0.11.dist-info/top_level.txt
check_link-0.0.11.dist-info/RECORD
