Metadata-Version: 2.1
Name: check_link
Version: 0.0.11
Summary: Check if URL is available
Author-email: DataShades <datashades@linkdigital.com.au>, Sergey Motornyuk <sergey.motornyuk@linkdigital.com.au>
Maintainer-email: DataShades <datashades@linkdigital.com.au>
License: AGPL
Project-URL: Homepage, https://github.com/DataShades/check-link
Keywords: URL,validator,HTTP
Classifier: Development Status :: 4 - Beta
Classifier: License :: OSI Approved :: GNU Affero General Public License v3 or later (AGPLv3+)
Classifier: Programming Language :: Python :: 3.7
Classifier: Programming Language :: Python :: 3.8
Classifier: Programming Language :: Python :: 3.9
Classifier: Programming Language :: Python :: 3.10
Requires-Python: >=3.7
Requires-Dist: httpx
Requires-Dist: requests
Provides-Extra: cli
Requires-Dist: click ; extra == 'cli'
Provides-Extra: dev
Requires-Dist: pytest ; extra == 'dev'
Requires-Dist: pytest-asyncio ; extra == 'dev'
Requires-Dist: pytest-httpx ; extra == 'dev'
Requires-Dist: pytest-cov ; extra == 'dev'
Requires-Dist: aioresponses ; extra == 'dev'
Requires-Dist: responses ; extra == 'dev'
Requires-Dist: faker ; extra == 'dev'
Provides-Extra: faster
